dora/__init__.py
dora/isa.py
dora/ml.py
dora/interface/Interfaces.py
dora/interface/__init__.py
dora/interface/generic.py
dora/interface/jupyter.py
dora/interface/zeppelin.py
dora/template/cp/score/code_score.py
dora/template/cp/score/init.py
dora_isa-0.2.1.24.data/data/lib/python3.7/site-packages/dora/template/Dockerfile
dora_isa-0.2.1.24.data/data/lib/python3.7/site-packages/dora/template/cp/score/run.sh
dora_isa-0.2.1.24.dist-info/METADATA
dora_isa-0.2.1.24.dist-info/WHEEL
dora_isa-0.2.1.24.dist-info/top_level.txt
dora_isa-0.2.1.24.dist-info/RECORD
