Metadata-Version: 2.1
Name: dora-isa
Version: 0.2.1.24
Summary: SQL Parser for Dora Project
Home-page: http://www.compasso.com.br
Author: didone
Author-email: tiago.didone@compasso.com.br
License: UNKNOWN
Platform: UNKNOWN
Classifier: Programming Language :: Python :: 3
Classifier: Operating System :: OS Independent
